{"scope":{"breadcrumbs":[{"timestamp":1748549697.823,"category":"console","level":"log","message":"d {\n  _notifyingListeners: false,\n  _scopeListeners: [ [Function: o] ],\n  _eventProcessors: [],\n  _breadcrumbs: [],\n  _attachments: [],\n  _user: {},\n  _tags: {},\n  _extra: {},\n  _contexts: {},\n  _sdkProcessingMetadata: {},\n  _propagationContext: {\n    traceId: 'ea1bae82377e432bab39f5ea814716cb',\n    spanId: '8a431bae28b3a2e3'\n  },\n  _client: k {\n    _options: {\n      _metadata: [Object],\n      ipcMode: 3,\n      getSessions: [Function: getSessions],\n      dsn: 'https://739bbcfc0ba4481481138d3fc831136d@o95242.ingest.sentry.io/4504451487301632',\n      beforeSend: [Function (anonymous)],\n      debug: false,\n      release: 'balenaEtcher@2.1.0',\n      environment: 'production',\n      autoSessionTracking: false,\n      stackParser: [Function (anonymous)],\n      defaultIntegrations: [Array],\n      transport: [Function (anonymous)],\n      instrumenter: 'sentry',\n      integrations: [Array],\n      transportOptions: [Object],\n      platform: 'node',\n      runtime: [Object],\n      serverName: 'BobTony'\n    },\n    _integrations: {\n      SentryMinidump: [Object],\n      ElectronBreadcrumbs: [Object],\n      Net: [Object],\n      MainContext: [Object],\n      ChildProcess: [Object],\n      OnUncaughtException: [Object],\n      PreloadInjection: [Object],\n      AdditionalContext: [Object],\n      Screenshots: [Object],\n      RendererProfiling: [Object],\n      InboundFilters: [Object],\n      FunctionToString: [Object],\n      LinkedErrors: [Object],\n      RequestData: [Object],\n      Console: [Object],\n      Http: [Me],\n      Undici: [_t],\n      OnUnhandledRejection: [Object],\n      ContextLines: [Object],\n      LocalVariables: [Object],\n      Modules: [Object],\n      MainProcessSession: [Object]\n    },\n    _integrationsInitialized: true,\n    _numProcessing: 0,\n    _outcomes: {},\n    _hooks: { preprocessEvent: [Array] },\n    _eventProcessors: [\n      [Function],\n      [Function],\n      [Function],\n      [Function],\n      [Function],\n      [Function],\n      [Function],\n      [Function]\n    ],\n    _dsn: {\n      protocol: 'https',\n      publicKey: '739bbcfc0ba4481481138d3fc831136d',\n      pass: '',\n      host: 'o95242.ingest.sentry.io',\n      port: '',\n      path: '',\n      projectId: '4504451487301632'\n    },\n    _transport: { send: [Function], flush: [Function: flush] }\n  },\n  _session: {\n    sid: '9d172ec72415486f9c3733a03a5756ec',\n    init: true,\n    timestamp: 1748549697.8218646,\n    started: 1748549697.8218033,\n    duration: 0.00006127357482910156,\n    status: 'ok',\n    errors: 0,\n    ignoreDuration: false,\n    toJSON: [Function: toJSON],\n    did: undefined,\n    release: 'balenaEtcher@2.1.0',\n    environment: 'production'\n  }\n}"},{"timestamp":1748549697.884,"category":"electron","message":"app.will-finish-launching","type":"ui"},{"timestamp":1748549697.887,"category":"electron","message":"app.ready","type":"ui"},{"timestamp":1748549697.892,"category":"electron","message":"app.session-created","type":"ui"},{"timestamp":1748549697.92,"category":"electron","message":"app.web-contents-created","type":"ui"},{"timestamp":1748549697.923,"category":"electron","message":"app.browser-window-created","type":"ui"},{"timestamp":1748549698.207,"category":"electron","message":"app.gpu-info-update","type":"ui"},{"timestamp":1748549698.548,"category":"console","level":"log","message":"Language changed to: en"},{"timestamp":1748549698.573,"category":"electron","message":"renderer.dom-ready","type":"ui","data":{"id":1,"url":"app:///.webpack/renderer/main_window/index.html"}},{"timestamp":1748549698.574,"category":"console","level":"log","message":"ready-to-show: 749.577ms"},{"timestamp":1748549698.575,"category":"electron","message":"window.show","type":"ui","data":{"id":1,"url":"app:///.webpack/renderer/main_window/index.html"}},{"timestamp":1748549698.595,"category":"console","data":{"arguments":["Starting..."],"logger":"console"},"level":"log","message":"Starting..."},{"timestamp":1748549698.61,"category":"electron","message":"window.focus","type":"ui","data":{"id":1,"url":"app:///.webpack/renderer/main_window/index.html"}},{"timestamp":1748549698.61,"category":"electron","message":"app.browser-window-focus","type":"ui"},{"timestamp":1748549698.616,"category":"console","data":{"arguments":["Starting..."],"logger":"console"},"level":"log","message":"Starting..."},{"timestamp":1748549698.621,"category":"console","data":{"arguments":["Starting..."],"logger":"console"},"level":"log","message":"Starting..."},{"timestamp":1748549698.624,"category":"console","data":{"arguments":["/home/lennilid/Downloads/usr/lib/balena-etcher/resources/etcher-util"],"logger":"console"},"level":"log","message":"/home/lennilid/Downloads/usr/lib/balena-etcher/resources/etcher-util"},{"timestamp":1748549698.63,"category":"console","data":{"arguments":["etcher-lsl22"],"logger":"console"},"level":"log","message":"etcher-lsl22"},{"timestamp":1748549698.64,"category":"console","data":{"arguments":["Retrying to connect to child process in 1000... 1 / 10"],"logger":"console"},"level":"log","message":"Retrying to connect to child process in 1000... 1 / 10"},{"timestamp":1748549698.645,"category":"console","level":"log","message":"packageUpdatable false"},{"timestamp":1748549699.641,"category":"console","data":{"arguments":["etcher-lsl22"],"logger":"console"},"level":"log","message":"etcher-lsl22"},{"timestamp":1748549699.645,"category":"console","data":{"arguments":["CHILD READY"],"logger":"console"},"level":"log","message":"CHILD READY"},{"timestamp":1748549699.646,"category":"console","data":{"arguments":["start heartbeat"],"logger":"console"},"level":"log","message":"start heartbeat"},{"timestamp":1748549699.646,"category":"console","data":{"arguments":["CHILD LOG: Ready ..."],"logger":"console"},"level":"log","message":"CHILD LOG: Ready ..."},{"timestamp":1748549699.647,"category":"console","data":{"arguments":["CHILD LOG: Scan requested"],"logger":"console"},"level":"log","message":"CHILD LOG: Scan requested"},{"timestamp":1748549699.674,"category":"console","data":{"arguments":["Starting..."],"logger":"console"},"level":"log","message":"Starting..."},{"timestamp":1748549699.684,"category":"console","data":{"arguments":["Starting..."],"logger":"console"},"level":"log","message":"Starting..."},{"timestamp":1748549699.854,"category":"fetch","data":{"method":"POST","url":"https://data.balena-cloud.com/amplitude/2/httpapi","status_code":200},"type":"http"},{"timestamp":1748549699.855,"category":"console","data":{"arguments":["Amplitude Logger [Warn]: {code: 0, error: \"Status 'unknown' provided for 3 events\"}"],"logger":"console"},"level":"warning","message":"Amplitude Logger [Warn]: {code: 0, error: \"Status 'unknown' provided for 3 events\"}"},{"timestamp":1748549700.99,"category":"fetch","data":{"method":"POST","url":"https://data.balena-cloud.com/amplitude/2/httpapi","status_code":200},"type":"http"},{"timestamp":1748549700.991,"category":"console","data":{"arguments":["Amplitude Logger [Warn]: {code: 0, error: \"Status 'unknown' provided for 3 events\"}"],"logger":"console"},"level":"warning","message":"Amplitude Logger [Warn]: {code: 0, error: \"Status 'unknown' provided for 3 events\"}"},{"timestamp":1748549702.631,"category":"ui.click","message":"button.StyledButton-sc-323bzc-0.fvTByX.sc-bqWxrE.sc-bjfHbI.bDnjBG.cbRKZK.sc-dIfARi.jhuGii.sc-hQIyOC.hUDWjp[type=\"button\"]"},{"timestamp":1748549702.635,"category":"console","data":{"arguments":["Starting..."],"logger":"console"},"level":"log","message":"Starting..."},{"timestamp":1748549703.125,"category":"fetch","data":{"method":"POST","url":"https://data.balena-cloud.com/amplitude/2/httpapi","status_code":200},"type":"http"},{"timestamp":1748549703.126,"category":"console","data":{"arguments":["Amplitude Logger [Warn]: {code: 0, error: \"Status 'unknown' provided for 3 events\"}"],"logger":"console"},"level":"warning","message":"Amplitude Logger [Warn]: {code: 0, error: \"Status 'unknown' provided for 3 events\"}"},{"timestamp":1748549706.264,"category":"fetch","data":{"method":"POST","url":"https://data.balena-cloud.com/amplitude/2/httpapi","status_code":200},"type":"http"},{"timestamp":1748549706.265,"category":"console","data":{"arguments":["Amplitude Logger [Warn]: {code: 0, error: \"Status 'unknown' provided for 3 events\"}"],"logger":"console"},"level":"warning","message":"Amplitude Logger [Warn]: {code: 0, error: \"Status 'unknown' provided for 3 events\"}"},{"timestamp":1748549710.393,"category":"fetch","data":{"method":"POST","url":"https://data.balena-cloud.com/amplitude/2/httpapi","status_code":200},"type":"http"},{"timestamp":1748549710.393,"category":"console","data":{"arguments":["Amplitude Logger [Warn]: {code: 0, error: \"Status 'unknown' provided for 3 events\"}"],"logger":"console"},"level":"warning","message":"Amplitude Logger [Warn]: {code: 0, error: \"Status 'unknown' provided for 3 events\"}"},{"timestamp":1748549710.394,"category":"console","data":{"arguments":["Amplitude Logger [Error]: Event rejected due to exceeded retry count"],"logger":"console"},"level":"error","message":"Amplitude Logger [Error]: Event rejected due to exceeded retry count"},{"timestamp":1748549710.394,"category":"console","data":{"arguments":["Amplitude Logger [Error]: Event rejected due to exceeded retry count"],"logger":"console"},"level":"error","message":"Amplitude Logger [Error]: Event rejected due to exceeded retry count"},{"timestamp":1748549710.394,"category":"console","data":{"arguments":["Amplitude Logger [Error]: Event rejected due to exceeded retry count"],"logger":"console"},"level":"error","message":"Amplitude Logger [Error]: Event rejected due to exceeded retry count"},{"timestamp":1748549725.843,"category":"ui.click","message":"button.StyledButton-sc-323bzc-0.fvTByX.sc-bqWxrE.sc-bjfHbI.bDnjBG.cbRKZK.sc-dIfARi.jhuGii.sc-bTtZEv.iPtkei.sc-fSKiAx.gPjwie.sc-bATJPV.bwtIbN[type=\"button\"]"},{"timestamp":1748549725.959,"category":"electron","message":"window.blur","type":"ui","data":{"id":1,"url":"app:///.webpack/renderer/main_window/index.html"}},{"timestamp":1748549725.959,"category":"electron","message":"app.browser-window-blur","type":"ui"},{"timestamp":1748549727.042,"category":"fetch","data":{"method":"POST","url":"https://data.balena-cloud.com/amplitude/2/httpapi","status_code":200},"type":"http"},{"timestamp":1748549727.042,"category":"console","data":{"arguments":["Amplitude Logger [Warn]: {code: 0, error: \"Status 'unknown' provided for 1 events\"}"],"logger":"console"},"level":"warning","message":"Amplitude Logger [Warn]: {code: 0, error: \"Status 'unknown' provided for 1 events\"}"},{"timestamp":1748549728.341,"category":"fetch","data":{"method":"POST","url":"https://data.balena-cloud.com/amplitude/2/httpapi","status_code":200},"type":"http"},{"timestamp":1748549728.342,"category":"console","data":{"arguments":["Amplitude Logger [Warn]: {code: 0, error: \"Status 'unknown' provided for 1 events\"}"],"logger":"console"},"level":"warning","message":"Amplitude Logger [Warn]: {code: 0, error: \"Status 'unknown' provided for 1 events\"}"},{"timestamp":1748549730.475,"category":"fetch","data":{"method":"POST","url":"https://data.balena-cloud.com/amplitude/2/httpapi","status_code":200},"type":"http"},{"timestamp":1748549730.476,"category":"console","data":{"arguments":["Amplitude Logger [Warn]: {code: 0, error: \"Status 'unknown' provided for 1 events\"}"],"logger":"console"},"level":"warning","message":"Amplitude Logger [Warn]: {code: 0, error: \"Status 'unknown' provided for 1 events\"}"},{"timestamp":1748549733.607,"category":"fetch","data":{"method":"POST","url":"https://data.balena-cloud.com/amplitude/2/httpapi","status_code":200},"type":"http"},{"timestamp":1748549733.607,"category":"console","data":{"arguments":["Amplitude Logger [Warn]: {code: 0, error: \"Status 'unknown' provided for 1 events\"}"],"logger":"console"},"level":"warning","message":"Amplitude Logger [Warn]: {code: 0, error: \"Status 'unknown' provided for 1 events\"}"},{"timestamp":1748549734.811,"category":"electron","message":"window.focus","type":"ui","data":{"id":1,"url":"app:///.webpack/renderer/main_window/index.html"}},{"timestamp":1748549734.811,"category":"electron","message":"app.browser-window-focus","type":"ui"},{"timestamp":1748549734.821,"category":"console","data":{"arguments":["CHILD LOG: sourceMetadata requested"],"logger":"console"},"level":"log","message":"CHILD LOG: sourceMetadata requested"},{"timestamp":1748549734.832,"category":"console","data":{"arguments":["Starting..."],"logger":"console"},"level":"log","message":"Starting..."},{"timestamp":1748549735.734,"category":"fetch","data":{"method":"POST","url":"https://data.balena-cloud.com/amplitude/2/httpapi","status_code":200},"type":"http"},{"timestamp":1748549735.734,"category":"console","data":{"arguments":["Amplitude Logger [Warn]: {code: 0, error: \"Status 'unknown' provided for 2 events\"}"],"logger":"console"},"level":"warning","message":"Amplitude Logger [Warn]: {code: 0, error: \"Status 'unknown' provided for 2 events\"}"},{"timestamp":1748549736.858,"category":"fetch","data":{"method":"POST","url":"https://data.balena-cloud.com/amplitude/2/httpapi","status_code":200},"type":"http"},{"timestamp":1748549736.859,"category":"console","data":{"arguments":["Amplitude Logger [Warn]: {code: 0, error: \"Status 'unknown' provided for 2 events\"}"],"logger":"console"},"level":"warning","message":"Amplitude Logger [Warn]: {code: 0, error: \"Status 'unknown' provided for 2 events\"}"},{"timestamp":1748549737.982,"category":"fetch","data":{"method":"POST","url":"https://data.balena-cloud.com/amplitude/2/httpapi","status_code":200},"type":"http"},{"timestamp":1748549737.983,"category":"console","data":{"arguments":["Amplitude Logger [Warn]: {code: 0, error: \"Status 'unknown' provided for 1 events\"}"],"logger":"console"},"level":"warning","message":"Amplitude Logger [Warn]: {code: 0, error: \"Status 'unknown' provided for 1 events\"}"},{"timestamp":1748549737.983,"category":"console","data":{"arguments":["Amplitude Logger [Error]: Event rejected due to exceeded retry count"],"logger":"console"},"level":"error","message":"Amplitude Logger [Error]: Event rejected due to exceeded retry count"},{"timestamp":1748549739.116,"category":"fetch","data":{"method":"POST","url":"https://data.balena-cloud.com/amplitude/2/httpapi","status_code":200},"type":"http"},{"timestamp":1748549739.117,"category":"console","data":{"arguments":["Amplitude Logger [Warn]: {code: 0, error: \"Status 'unknown' provided for 2 events\"}"],"logger":"console"},"level":"warning","message":"Amplitude Logger [Warn]: {code: 0, error: \"Status 'unknown' provided for 2 events\"}"},{"timestamp":1748549742.24,"category":"fetch","data":{"method":"POST","url":"https://data.balena-cloud.com/amplitude/2/httpapi","status_code":200},"type":"http"},{"timestamp":1748549742.241,"category":"console","data":{"arguments":["Amplitude Logger [Warn]: {code: 0, error: \"Status 'unknown' provided for 2 events\"}"],"logger":"console"},"level":"warning","message":"Amplitude Logger [Warn]: {code: 0, error: \"Status 'unknown' provided for 2 events\"}"},{"timestamp":1748549746.373,"category":"fetch","data":{"method":"POST","url":"https://data.balena-cloud.com/amplitude/2/httpapi","status_code":200},"type":"http"},{"timestamp":1748549746.374,"category":"console","data":{"arguments":["Amplitude Logger [Warn]: {code: 0, error: \"Status 'unknown' provided for 2 events\"}"],"logger":"console"},"level":"warning","message":"Amplitude Logger [Warn]: {code: 0, error: \"Status 'unknown' provided for 2 events\"}"},{"timestamp":1748549746.374,"category":"console","data":{"arguments":["Amplitude Logger [Error]: Event rejected due to exceeded retry count"],"logger":"console"},"level":"error","message":"Amplitude Logger [Error]: Event rejected due to exceeded retry count"},{"timestamp":1748549746.374,"category":"console","data":{"arguments":["Amplitude Logger [Error]: Event rejected due to exceeded retry count"],"logger":"console"},"level":"error","message":"Amplitude Logger [Error]: Event rejected due to exceeded retry count"},{"timestamp":1748549767.359,"category":"ui.click","message":"div.sc-gKPRtg.cebezU.sc-iBYQkv.jDHmvD > p.sc-kGFDUS.kjxjwY > a"},{"timestamp":1748549768.488,"category":"fetch","data":{"method":"POST","url":"https://data.balena-cloud.com/amplitude/2/httpapi","status_code":200},"type":"http"},{"timestamp":1748549768.489,"category":"console","data":{"arguments":["Amplitude Logger [Warn]: {code: 0, error: \"Status 'unknown' provided for 1 events\"}"],"logger":"console"},"level":"warning","message":"Amplitude Logger [Warn]: {code: 0, error: \"Status 'unknown' provided for 1 events\"}"},{"timestamp":1748549768.567,"category":"ui.click","message":"button.StyledButton-sc-323bzc-0.gMGWqj.sc-bqWxrE.sc-hBxehG.bDnjBG.btTRHI.sc-dIfARi.ffhPfA[type=\"button\"]"},{"timestamp":1748549768.571,"category":"console","data":{"arguments":["Starting..."],"logger":"console"},"level":"log","message":"Starting..."}],"attachments":[],"contexts":{},"tags":{},"extra":{},"user":{},"fingerprint":[],"eventProcessors":[],"propagationContext":{"traceId":"ea1bae82377e432bab39f5ea814716cb","spanId":"8a431bae28b3a2e3"},"sdkProcessingMetadata":{}},"event":{"contexts":{"app":{"app_name":"balenaEtcher","app_version":"2.1.0","app_start_time":"2025-05-29T20:14:57.674Z"},"os":{"kernel_version":"6.12.28-1-MANJARO","name":"Ubuntu Linux","version":"\"25.0.3\""},"browser":{"name":"Chrome"},"chrome":{"name":"Chrome","type":"runtime","version":"124.0.6367.60"},"device":{"arch":"x64","family":"Desktop"},"node":{"name":"Node","type":"runtime","version":"20.11.1"},"runtime":{"name":"Electron","version":"30.0.1"}},"environment":"production","release":"balenaEtcher@2.1.0","user":{"ip_address":"{{auto}}"},"tags":{"event.origin":"electron","event.environment":"javascript","event.process":"browser","event_type":"javascript"}}}